{"NOM": {"NO_PREPOSITION": ["« На метле или в пене морей , / Всех чудес на свете милей / Ты -- убежище муки моей , / Женщина ! »", "Убежище -- гордость управдома . \" Культурненько \", -- говорил он .", "Мой дом / это моя надежда / моё убежище ."]}, "ACC": {"NO_PREPOSITION": ["Ищите убежище , пока не поздно , сэр !", "Для животных , не умеющих поддерживать постоянную температуру тела , проще всего подыскать для себя тёплое убежище ."], "В + ACC": ["Населению предлагалось организованно спуститься в убежища ."]}, "GEN": {"NO_PREPOSITION": ["-- Я и то думаю , -- вздохнул человек , -- может , политического убежища спросить ?", "Премьер-министр Михаил Касьянов делал одно за другим заявления в том духе , что врагам бывшего друга протянута рука дружбы :\" Вопрос о предоставлении убежища президенту Милошевичу не стоит ..."], "ИЗ + GEN": ["Первое время Ольга вовсе не выходила из своего оригинального убежища , опасаясь быть обнаруженной как-нибудь невзначай , и даже справляла нужду в горшок , который племянница Вера подавала ей дважды в день ."]}, "LOC": {"NO_PREPOSITION": [], "В + LOC": ["А в убежище было зловеще светло ."]}, "DAT": {"NO_PREPOSITION": []}, "INS": {"NO_PREPOSITION": []}}