{"NOM": {"NO_PREPOSITION": ["Мечтая о доме и живя с родителями в двухкомнатной квартирке , Алексей Тихонович Благодуров решил жениться , не имея при этом никакой склонности к семейной жизни , но ведь дом для одного человека -- дичь и чушь , дому обязательно нужна семья .", "Чушь !", "Чушь невероятная .", "Чушь , да ?", "Это чушь абсолютная , поскольку есть показания губернатора Самары Титова , есть показания генерального директора \" АвтоВАЗа \" Каданникова , где они абсолютно точно утверждают , что всё это выдумка Генпрокуратуры , что было соответствующее решение законодательного собрания Самары , соответствующее решение Совета директоров \" АвтоВАЗа \" по поводу этой сделки , и подтверждение Минфина России , что эта сделка абсолютно легитимна , законна ."]}, "ACC": {"NO_PREPOSITION": ["А когда человек несет реальную чушь , не предлагая ничего взамен - что это по-вашему ?", "Как же вы допускаете , чтобы ваша жена говорила , простите меня , такую чушь ?"], "ЗА + ACC": ["Че за чушь несёт ."]}, "GEN": {"NO_PREPOSITION": [], "ОТ + GEN": ["Ещё что-то прошелестела в ухо , завядшее от бабской чуши ."]}, "LOC": {"NO_PREPOSITION": []}, "DAT": {"NO_PREPOSITION": []}, "INS": {"NO_PREPOSITION": ["И той безвкусной / пошлой / надменной чушью / которую она порола / разница немыслимая / как другой человек ."]}}